eav
tests
