Metadata-Version: 1.2
Name: travisb-django-eav2
Version: 0.13.921
Summary: Entity-Attribute-Value storage for Django. Fork of django-eav-2 by Iwo Herka [hi@iwoherka.eu]
Home-page: http://github.com/sree93/django-eav2
Maintainer: Srinath Menon
Maintainer-email: srinath@travisbickle.tech
License: GNU Lesser General Public License (LGPL), Version 3
Platform: UNKNOWN
Classifier: Development Status :: 3 - Alpha
Classifier: Environment :: Web Environment
Classifier: Framework :: Django
Classifier: Intended Audience :: Developers
Classifier: License :: OSI Approved :: GNU Library or Lesser General Public License (LGPL)
Classifier: Programming Language :: Python
Classifier: Topic :: Database
Classifier: Topic :: Software Development :: Libraries :: Python Modules
Requires: python (>= 3.5)
Requires: django (>= 1.11.14)
Provides: eav
